backend_microservice/.dockerignore
backend_microservice/__init__.py
backend_microservice/app.py
backend_microservice/app_factory.py
backend_microservice/config.py
backend_microservice/Dockerfile
backend_microservice/feedback_data.json
backend_microservice/routes/__init__.py
backend_microservice/routes/chat.py
backend_microservice/routes/feedback.py
backend_microservice/routes/health.py
backend_microservice/routes/model_comparison.py
backend_microservice/routes/prediction.py
backend_microservice/routes/upload.py
backend_microservice/static/content.html
backend_microservice/static/index.html
backend_microservice/static/index_v2_backup.html
backend_microservice/static/index_v2_functioning.html
backend_microservice/static/script.js
backend_microservice/static/styles.css
cv2_group/.coverage
cv2_group/__init__.py
cv2_group/data/__init__.py
cv2_group/data/data_ingestion.py
cv2_group/data/data_processing.py
cv2_group/data/data_validation.py
cv2_group/features/__init__.py
cv2_group/features/feature_extraction.py
cv2_group/features/feature_scaling.py
cv2_group/features/feature_selection.py
cv2_group/models/__init__.py
cv2_group/models/model_definitions.py
cv2_group/models/model_evaluation.py
cv2_group/models/model_saving.py
cv2_group/models/model_training.py
cv2_group/models/pydantic_models.py
cv2_group/utils/__init__.py
cv2_group/utils/api_models.py
cv2_group/utils/azure_blob.py
cv2_group/utils/azure_integration.py
cv2_group/utils/azure_model_loader.py
cv2_group/utils/binary.py
cv2_group/utils/configuration.py
cv2_group/utils/dashboard_stats.py
cv2_group/utils/feedback_system.py
cv2_group/utils/helpers.py
cv2_group/utils/image_helpers.py
cv2_group/utils/image_processing.py
cv2_group/utils/llama_service.py
cv2_group/utils/predicting.py
cv2_group/utils/streamlit_integration.py
cv2_group/utils/streamlit_visualization.py
cv2_group/utils/visualization.py
cv2_group-1.0.0.dist-info/entry_points.txt
cv2_group-1.0.0.dist-info/METADATA
cv2_group-1.0.0.dist-info/WHEEL
cv2_group-1.0.0.dist-info/RECORD
