Metadata-Version: 2.3
Name: cv2_group
Version: 1.0.0
Summary: A versatile toolkit to analyze roots within petri dishes.
License: MIT
Author: Yorbe Heeren
Author-email: 232922@buas.nl
Requires-Python: ==3.10.11
Classifier: License :: OSI Approved :: MIT License
Classifier: Programming Language :: Python :: 3
Requires-Dist: apache-airflow (==2.9.1)
Requires-Dist: app (>=0.0.1,<0.0.2)
Requires-Dist: azure-ai-ml (==1.14.0)
Requires-Dist: azure-identity (>=1.16.0,<2.0.0)
Requires-Dist: azure-keyvault-secrets (>=4.10.0,<5.0.0)
Requires-Dist: azure-storage-blob (>=12.19.0,<12.20.0)
Requires-Dist: azureml-core
Requires-Dist: azureml-dataprep[fuse,pandas]
Requires-Dist: azureml-defaults (>=1.55.0,<1.56.0)
Requires-Dist: azureml-mlflow (>=1.55.0,<1.56.0)
Requires-Dist: azureml-pipeline (>=1.55.0,<1.56.0)
Requires-Dist: azureml-pipeline-core (>=1.55.0,<1.56.0)
Requires-Dist: azureml-pipeline-steps (>=1.55.0,<1.56.0)
Requires-Dist: azureml-train (>=1.55.0,<1.56.0)
Requires-Dist: azureml-train-core (>=1.55.0,<1.56.0)
Requires-Dist: click (==8.1.3)
Requires-Dist: docker (==7.1.0)
Requires-Dist: fastapi (==0.110.0)
Requires-Dist: fusepy
Requires-Dist: ghp-import (==2.1.0)
Requires-Dist: load-config (>=0.2.0b6,<0.3.0)
Requires-Dist: marshmallow (==3.19.0)
Requires-Dist: matplotlib (==3.8.4)
Requires-Dist: mlflow[azureml] (>=3.1.0,<4.0.0)
Requires-Dist: numpy (==1.23.5)
Requires-Dist: opencv-python (==4.10.0.84)
Requires-Dist: patchify (==0.2.3)
Requires-Dist: pendulum (==2.1.2)
Requires-Dist: pillow (==10.3.0)
Requires-Dist: protobuf (>=3.9.2,<3.20)
Requires-Dist: pytest (==8.3.0)
Requires-Dist: pytest-cov (==6.1.1)
Requires-Dist: python-dotenv (>=1.1.1,<2.0.0)
Requires-Dist: python-multipart (>=0.0.20,<0.0.21)
Requires-Dist: scikit-image (==0.22.0)
Requires-Dist: scikit-learn (>=1.6.1,<2.0.0)
Requires-Dist: setuptools (>=65.5.0,<65.6.0)
Requires-Dist: streamlit (==1.22.0)
Requires-Dist: tensorflow (==2.10.0)
Requires-Dist: tensorflow-io-gcs-filesystem (==0.26.0)
Requires-Dist: tk (>=0.1.0,<0.2.0)
Requires-Dist: typer (==0.9.0)
Requires-Dist: uvicorn (==0.29.0)
Requires-Dist: wandb (==0.16.6)
